odoo/addons/account_fiscal_position_type/README.rst
odoo/addons/account_fiscal_position_type/__init__.py
odoo/addons/account_fiscal_position_type/__manifest__.py
odoo/addons/account_fiscal_position_type/demo/account_chart_template.xml
odoo/addons/account_fiscal_position_type/demo/account_fiscal_position.xml
odoo/addons/account_fiscal_position_type/demo/account_fiscal_position_template.xml
odoo/addons/account_fiscal_position_type/demo/res_groups.xml
odoo/addons/account_fiscal_position_type/i18n/account_fiscal_position_type.pot
odoo/addons/account_fiscal_position_type/i18n/es.po
odoo/addons/account_fiscal_position_type/i18n/fr.po
odoo/addons/account_fiscal_position_type/i18n/it.po
odoo/addons/account_fiscal_position_type/models/__init__.py
odoo/addons/account_fiscal_position_type/models/account_chart_template.py
odoo/addons/account_fiscal_position_type/models/account_fiscal_position.py
odoo/addons/account_fiscal_position_type/models/account_fiscal_position_template.py
odoo/addons/account_fiscal_position_type/models/account_move.py
odoo/addons/account_fiscal_position_type/readme/CONFIGURE.rst
odoo/addons/account_fiscal_position_type/readme/DESCRIPTION.rst
odoo/addons/account_fiscal_position_type/static/description/fiscal_position_form.png
odoo/addons/account_fiscal_position_type/static/description/icon.png
odoo/addons/account_fiscal_position_type/static/description/index.html
odoo/addons/account_fiscal_position_type/tests/__init__.py
odoo/addons/account_fiscal_position_type/tests/test_module.py
odoo/addons/account_fiscal_position_type/views/view_account_fiscal_position.xml
odoo/addons/account_fiscal_position_type/views/view_account_fiscal_position_template.xml
odoo/addons/account_fiscal_position_type/views/view_account_move.xml
odoo_addon_account_fiscal_position_type-16.0.1.0.4.dist-info/METADATA
odoo_addon_account_fiscal_position_type-16.0.1.0.4.dist-info/WHEEL
odoo_addon_account_fiscal_position_type-16.0.1.0.4.dist-info/top_level.txt
odoo_addon_account_fiscal_position_type-16.0.1.0.4.dist-info/RECORD
